odoo10_addon_web_notify-10.0.1.2.0-py2.7-nspkg.pth
odoo/addons/web_notify/README.rst
odoo/addons/web_notify/__init__.py
odoo/addons/web_notify/__manifest__.py
odoo/addons/web_notify/i18n/de.po
odoo/addons/web_notify/i18n/es.po
odoo/addons/web_notify/i18n/hr.po
odoo/addons/web_notify/i18n/lt.po
odoo/addons/web_notify/i18n/nl_NL.po
odoo/addons/web_notify/i18n/pt_BR.po
odoo/addons/web_notify/i18n/web_notify.pot
odoo/addons/web_notify/models/__init__.py
odoo/addons/web_notify/models/res_users.py
odoo/addons/web_notify/static/description/icon.png
odoo/addons/web_notify/static/description/notifications_screenshot.png
odoo/addons/web_notify/static/src/css/notification.less
odoo/addons/web_notify/static/src/js/notification.js
odoo/addons/web_notify/static/src/js/web_client.js
odoo/addons/web_notify/static/src/xml/notification.xml
odoo/addons/web_notify/tests/__init__.py
odoo/addons/web_notify/tests/test_res_users.py
odoo/addons/web_notify/views/web_notify.xml
odoo10_addon_web_notify-10.0.1.2.0.dist-info/METADATA
odoo10_addon_web_notify-10.0.1.2.0.dist-info/RECORD
odoo10_addon_web_notify-10.0.1.2.0.dist-info/WHEEL
odoo10_addon_web_notify-10.0.1.2.0.dist-info/namespace_packages.txt
odoo10_addon_web_notify-10.0.1.2.0.dist-info/top_level.txt
